README.md
setup.cfg
setup.py
iglsynth/__init__.py
iglsynth/version.py
iglsynth.egg-info/PKG-INFO
iglsynth.egg-info/SOURCES.txt
iglsynth.egg-info/dependency_links.txt
iglsynth.egg-info/requires.txt
iglsynth.egg-info/top_level.txt
iglsynth/game/__init__.py
iglsynth/game/arena.py
iglsynth/game/core.py
iglsynth/game/game.py
iglsynth/game/gridworld.py
iglsynth/game/kripke.py
iglsynth/game/tsys.py
iglsynth/game/tests/__init__.py
iglsynth/game/tests/test_action.py
iglsynth/game/tests/test_arena.py
iglsynth/game/tests/test_game.py
iglsynth/game/tests/test_gridworld.py
iglsynth/game/tests/test_kripke.py
iglsynth/game/tests/test_tsys.py
iglsynth/logic/__init__.py
iglsynth/logic/core.py
iglsynth/logic/ltl.py
iglsynth/logic/tests/__init__.py
iglsynth/logic/tests/test_alphabet.py
iglsynth/logic/tests/test_ap.py
iglsynth/logic/tests/test_ltl.py
iglsynth/logic/tests/test_pl.py
iglsynth/solver/__init__.py
iglsynth/solver/core.py
iglsynth/solver/zielonka.py
iglsynth/solver/tests/__init__.py
iglsynth/util/__init__.py
iglsynth/util/graph.py
iglsynth/util/spot.py
iglsynth/util/tests/__init__.py
iglsynth/util/tests/test_graph.py
iglsynth/util/tests/test_spot.py